biolord/__init__.py
biolord/_constants.py
biolord/_data.py
biolord/_model.py
biolord/_module.py
biolord/_train.py
biolord/_utils.py
biolord-0.0.3.dist-info/METADATA
biolord-0.0.3.dist-info/WHEEL
biolord-0.0.3.dist-info/licenses/LICENSE
biolord-0.0.3.dist-info/RECORD
