Metadata-Version: 2.1
Name: biolord
Version: 0.0.3
Summary: A deep generative framework for disentangling known and unknown attributes in single-cell data.
Project-URL: Documentation, https://biolord.readthedocs.io/
Project-URL: Source, https://github.com/nitzanlab/biolord
Project-URL: Home-page, https://github.com/nitzanlab/biolord
Author: Zoe Piran
Maintainer-email: Zoe Piran <zoe.piran@mail.huji.ac.il>
License: BSD 3-Clause License
License-File: LICENSE
Requires-Python: >3.8
Requires-Dist: anndata
Requires-Dist: rich
Requires-Dist: scanpy
Requires-Dist: scikit-learn
Requires-Dist: scvi-tools
Requires-Dist: session-info
Requires-Dist: torch
Provides-Extra: dev
Requires-Dist: bump2version; extra == 'dev'
Requires-Dist: pre-commit; extra == 'dev'
Requires-Dist: twine>=4.0.2; extra == 'dev'
Provides-Extra: doc
Requires-Dist: ipython; extra == 'doc'
Requires-Dist: myst-nb; extra == 'doc'
Requires-Dist: sphinx-autodoc-typehints; extra == 'doc'
Requires-Dist: sphinx-book-theme>=1.0.0; extra == 'doc'
Requires-Dist: sphinx-copybutton; extra == 'doc'
Requires-Dist: sphinx>=5; extra == 'doc'
Requires-Dist: sphinxcontrib-bibtex>=1.0.0; extra == 'doc'
Provides-Extra: test
Requires-Dist: pytest; extra == 'test'
Requires-Dist: pytest-cov; extra == 'test'
